api_correios/APICorreios.py
api_correios/__init__.py
api_correios/schema/__init__.py
api_correios/schema/correios.py
api_correios/utils/token.py
api_correios-0.2.7.dist-info/LICENSE
api_correios-0.2.7.dist-info/WHEEL
api_correios-0.2.7.dist-info/METADATA
api_correios-0.2.7.dist-info/RECORD
