Metadata-Version: 2.1
Name: api-correios
Version: 0.2.7
Summary: Módulo de integração com a nova versão REST API dos Correios
License: MIT
Author: Bruno Souza
Author-email: bruno.souza@zaxapp.com.br
Requires-Python: >=3.6.12,<4.0.0
Classifier: License :: OSI Approved :: MIT License
Classifier: Programming Language :: Python :: 3
Classifier: Programming Language :: Python :: 3.10
Classifier: Programming Language :: Python :: 3.7
Classifier: Programming Language :: Python :: 3.8
Classifier: Programming Language :: Python :: 3.9
Requires-Dist: PyJWT (>=2.4.0,<3.0.0)
Requires-Dist: pydantic (>=1.9.1,<2.0.0)
Requires-Dist: requests (>=2.26.0,<3.0.0)
